LICENSE.txt
MANIFEST.in
README.rst
setup.py
pysmartprice/__init__.py
pysmartprice/abstract.py
pysmartprice/base.py
pysmartprice/constants.py
pysmartprice/helpers.py
pysmartprice/results.py
pysmartprice/smartparser.py
python_smartprice.egg-info/PKG-INFO
python_smartprice.egg-info/SOURCES.txt
python_smartprice.egg-info/dependency_links.txt
python_smartprice.egg-info/requires.txt
python_smartprice.egg-info/top_level.txt