Metadata-Version: 1.0
Name: python-smartprice
Version: 0.0.3
Summary: A simple scraping-based python library for MySmartPrice
Home-page: https://github.com/asifpy/python-smartprice
Author: Asif Jamadar
Author-email: saluasif@gmail.com
License: BSD License
Keywords: smartprice,price comparision,scrapping
Platform: UNKNOWN
